{
  "main": {
    "id": "e1fbda5feb563df9",
    "type": "split",
    "children": [
      {
        "id": "9ecd5d4f439f93bb",
        "type": "tabs",
        "children": [
          {
            "id": "f9f3cccb554ace8f",
            "type": "leaf",
            "state": {
              "type": "markdown",
              "state": {
                "file": "Concepts/Integers.md",
                "mode": "source",
                "source": false,
                "backlinks": true,
                "backlinkOpts": {
                  "collapseAll": false,
                  "extraContext": false,
                  "sortOrder": "alphabetical",
                  "showSearch": false,
                  "searchQuery": "",
                  "backlinkCollapsed": false,
                  "unlinkedCollapsed": true
                }
              },
              "icon": "lucide-file",
              "title": "Integers"
            }
          },
          {
            "id": "755d7411e7ef9489",
            "type": "leaf",
            "state": {
              "type": "markdown",
              "state": {
                "file": "2026-01-14.md",
                "mode": "source",
                "source": false,
                "backlinks": true,
                "backlinkOpts": {
                  "collapseAll": false,
                  "extraContext": false,
                  "sortOrder": "alphabetical",
                  "showSearch": false,
                  "searchQuery": "",
                  "backlinkCollapsed": false,
                  "unlinkedCollapsed": true
                }
              },
              "icon": "lucide-file",
              "title": "2026-01-14"
            }
          },
          {
            "id": "d06131fe68928e23",
            "type": "leaf",
            "state": {
              "type": "graph",
              "state": {},
              "icon": "lucide-git-fork",
              "title": "Graph view"
            }
          }
        ],
        "currentTab": 2
      }
    ],
    "direction": "vertical"
  },
  "left": {
    "id": "604170e0c21f028d",
    "type": "split",
    "children": [
      {
        "id": "81136a7489ce6a2f",
        "type": "tabs",
        "children": [
          {
            "id": "f24c31ba43483dce",
            "type": "leaf",
            "state": {
              "type": "file-explorer",
              "state": {
                "sortOrder": "alphabetical",
                "autoReveal": false
              },
              "icon": "lucide-folder-closed",
              "title": "Files"
            }
          },
          {
            "id": "32c3f6d0494ec730",
            "type": "leaf",
            "state": {
              "type": "search",
              "state": {
                "query": "tag:function",
                "matchingCase": false,
                "explainSearch": false,
                "collapseAll": false,
                "extraContext": false,
                "sortOrder": "alphabetical"
              },
              "icon": "lucide-search",
              "title": "Search"
            }
          },
          {
            "id": "04fcb8d2c6c93a53",
            "type": "leaf",
            "state": {
              "type": "bookmarks",
              "state": {},
              "icon": "lucide-bookmark",
              "title": "书签"
            }
          }
        ]
      }
    ],
    "direction": "horizontal",
    "width": 300
  },
  "right": {
    "id": "c657184ecfc8b6fa",
    "type": "split",
    "children": [
      {
        "id": "2d5db7eafdbca4e1",
        "type": "tabs",
        "children": [
          {
            "id": "42adfbdbc99b61e1",
            "type": "leaf",
            "state": {
              "type": "tag",
              "state": {
                "sortOrder": "frequency",
                "useHierarchy": true,
                "showSearch": false,
                "searchQuery": ""
              },
              "icon": "lucide-tags",
              "title": "Tags"
            }
          },
          {
            "id": "e9312ad7c9762096",
            "type": "leaf",
            "state": {
              "type": "backlink",
              "state": {
                "file": "Concepts/Cargo.md",
                "collapseAll": false,
                "extraContext": false,
                "sortOrder": "alphabetical",
                "showSearch": false,
                "searchQuery": "",
                "backlinkCollapsed": false,
                "unlinkedCollapsed": true
              },
              "icon": "links-coming-in",
              "title": "Backlinks for Cargo"
            }
          },
          {
            "id": "629e7f6689e35680",
            "type": "leaf",
            "state": {
              "type": "outgoing-link",
              "state": {
                "file": "Categories/Project.md",
                "linksCollapsed": false,
                "unlinkedCollapsed": true
              },
              "icon": "links-going-out",
              "title": "Outgoing links from Project"
            }
          },
          {
            "id": "6790ff27bd90e344",
            "type": "leaf",
            "state": {
              "type": "all-properties",
              "state": {
                "sortOrder": "frequency",
                "showSearch": false,
                "searchQuery": ""
              },
              "icon": "lucide-archive",
              "title": "All properties"
            }
          },
          {
            "id": "8e107ecb0caea730",
            "type": "leaf",
            "state": {
              "type": "outline",
              "state": {
                "file": "Concepts/Cargo.md",
                "followCursor": false,
                "showSearch": false,
                "searchQuery": ""
              },
              "icon": "lucide-list",
              "title": "Outline of Cargo"
            }
          },
          {
            "id": "3f878da409eced0c",
            "type": "leaf",
            "state": {
              "type": "git-view",
              "state": {},
              "icon": "git-pull-request",
              "title": "Source Control"
            }
          }
        ],
        "currentTab": 5
      }
    ],
    "direction": "horizontal",
    "width": 300
  },
  "left-ribbon": {
    "hiddenItems": {
      "switcher:Open quick switcher": false,
      "graph:Open graph view": false,
      "canvas:Create new canvas": false,
      "daily-notes:Open today's daily note": false,
      "templates:Insert template": false,
      "obsidian-git:Open Git source control": false,
      "command-palette:Open command palette": false,
      "obsidian-excalidraw-plugin:New drawing": false,
      "bases:Create new base": false,
      "remotely-save:Remotely Save": false
    }
  },
  "active": "d06131fe68928e23",
  "lastOpenFiles": [
    "2026-01-14.md",
    "Concepts/Integers.md",
    "Concepts/Integer Overflow.md",
    "Concepts/Integer Literals.md",
    "Concepts/Declaring Constants.md",
    "Concepts/Scalar.md",
    "Concepts/Shadowing.md",
    "Concepts/Signed.md",
    "Projects/Guessing Game.md",
    "Concepts/Control Flow.md",
    "Concepts/Unsigned.md",
    "Excalidraw/Drawing 2026-01-14 13.41.48.excalidraw.md",
    "Excalidraw",
    "Untitled.canvas",
    "Concepts/Data Types.md",
    "Concepts/Compound.md",
    "Concepts/Variables and Mutability.md",
    "Templates/Template-Concept.md",
    "Projects/The Very First Programme.md",
    "Concepts/Fuctions.md",
    "Concepts/Comments.md",
    "Concepts/Cargo.md",
    "Categories/Project.md",
    "Categories/Concepts.md",
    "Base/Common Concepts.base",
    "Templates/Template-Reference.md",
    "2026-01-13.md",
    "Base/2026-01-14.base",
    "Rust.md",
    "Base/2026-01-11.base",
    "Base/2026-01-13.base",
    "Daily.md",
    "Base/Rust.base",
    "Concepts",
    "Projects",
    "Daily",
    "Base/Projects.base"
  ]
}